edc_refusal/__init__.py
edc_refusal/admin.py
edc_refusal/admin_site.py
edc_refusal/apps.py
edc_refusal/auth_objects.py
edc_refusal/auths.py
edc_refusal/forms.py
edc_refusal/list_data.py
edc_refusal/managers.py
edc_refusal/model_mixins.py
edc_refusal/models.py
edc_refusal/urls.py
edc_refusal/utils.py
edc_refusal/migrations/0001_initial.py
edc_refusal/migrations/0002_historicalsubjectrefusal.py
edc_refusal/migrations/0003_auto_20220704_1841.py
edc_refusal/migrations/0004_refusalreasons_plural_name.py
edc_refusal/migrations/0005_alter_subjectrefusal_options_and_more.py
edc_refusal/migrations/0006_alter_subjectrefusal_managers.py
edc_refusal/migrations/0007_refusalreasons_extra_value.py
edc_refusal/migrations/0008_alter_historicalsubjectrefusal_device_created_and_more.py
edc_refusal/migrations/0009_alter_refusalreasons_options_and_more.py
edc_refusal/migrations/0010_alter_historicalsubjectrefusal_site_and_more.py
edc_refusal/migrations/__init__.py
edc_refusal/models/__init__.py
edc_refusal/models/list_models.py
edc_refusal/models/signals.py
edc_refusal/models/subject_refusal.py
edc_refusal/tests/__init__.py
edc_refusal/tests/models.py
edc_refusal/tests/test_settings.py
edc_refusal/tests/etc/user-aes-local.key
edc_refusal/tests/etc/user-aes-restricted.key
edc_refusal/tests/etc/user-rsa-local-private.pem
edc_refusal/tests/etc/user-rsa-local-public.pem
edc_refusal/tests/etc/user-rsa-restricted-private.pem
edc_refusal/tests/etc/user-rsa-restricted-public.pem
edc_refusal/tests/etc/user-salt-local.key
edc_refusal/tests/etc/user-salt-restricted.key
edc_refusal/tests/tests/__init__.py
edc_refusal/tests/tests/test_model.py
edc_refusal-1.0.1.dist-info/licenses/AUTHORS.rst
edc_refusal-1.0.1.dist-info/licenses/LICENSE
edc_refusal-1.0.1.dist-info/METADATA
edc_refusal-1.0.1.dist-info/WHEEL
edc_refusal-1.0.1.dist-info/top_level.txt
edc_refusal-1.0.1.dist-info/RECORD
